[
  {
    "id": 1,
    "username": "sofia_r",
    "location": "Berlin, Germany — Alexanderplatz",
    "imgUrl": "https://bullstrap.co/cdn/shop/files/8_a057052e-1024-41e2-9263-ecebadf509a5.png",
    "description": "Black leather wallet with metro card and student ID inside",
    "date": "2025-01-12"
  },
  {
    "id": 3,
    "username": "maya_g",
    "location": "Toronto, Canada — Union Station",
    "imgUrl": "https://ae01.alicdn.com/kf/S62553330325342ddbe66b1f835a1a8e72.jpg",
    "description": "iPhone 12 with a transparent case and a maple leaf sticker",
    "date": "2025-02-02"
  },

  {
    "id": 5,
    "username": "luca_p",
    "location": "Rome, Italy — Termini Station",
    "imgUrl": "https://u-mercari-images.mercdn.net/photos/m94392478022_2.jpg",
    "description": "Black Sony wireless headphones in a zip case",
    "date": "2025-02-28"
  },
  {
    "id": 6,
    "username": "amira_h",
    "location": "Cairo, Egypt — Tahrir Square",
    "imgUrl": "https://i.etsystatic.com/61605310/r/il/cb1c2d/7185938007/il_1588xN.7185938007_5p5o.jpg",
    "description": "Silver water bottle with Arabic calligraphy sticker",
    "date": "2025-03-05"
  }
]
